taguette/__init__.py
taguette/convert.py
taguette/database/__init__.py
taguette/database/base.py
taguette/database/copy.py
taguette/database/models.py
taguette/export.py
taguette/extract.py
taguette/import_codebook.py
taguette/main.py
taguette/migrations/env.py
taguette/migrations/script.py.mako
taguette/migrations/versions/09c662cd9483_make_documents_filename_not_null.py
taguette/migrations/versions/382db36f20f4_add_user_disabled.py
taguette/migrations/versions/43d6c240309d_remove_document_groups.py
taguette/migrations/versions/447d636f72c5_cascades.py
taguette/migrations/versions/491de2dc7cd7_add_indexes.py
taguette/migrations/versions/6489b5f9cfb5_increase_password_hash_size.py
taguette/migrations/versions/679f625e6e6a_fix_unique_tags.py
taguette/migrations/versions/807c0cc0ecf6_remove_invalid_hltags.py
taguette/migrations/versions/80b1cc9d4c22_add_user_email.py
taguette/migrations/versions/91ade71ccf4d_add_user_language.py
taguette/migrations/versions/b23f3b7a638e_add_user_password_change_date.py
taguette/migrations/versions/bc8e0e0677e9_rename_command_fields.py
taguette/migrations/versions/bce44849c2f2_lowercase_logins.py
taguette/migrations/versions/d86c45d7aa8a_add_document_direction.py
taguette/migrations/versions/db5e31a0233d_remove_blank_highlights.py
taguette/migrations/versions/dd37d9027a24_unique_tags.py
taguette/migrations/versions/e4cf92942271_add_index.py
taguette/migrations/versions/e4e090a5b511_remove_commands_document_id_fk.py
taguette/migrations/versions/ecb4065de575_don_t_use_server_default_now_timezone_.py
taguette/static/css/bootstrap.min.css
taguette/static/css/custom.css
taguette/static/css/fa-all.min.css
taguette/static/favicon.ico
taguette/static/js/bootstrap.bundle.min.js
taguette/static/js/bootstrap.bundle.min.js.map
taguette/static/js/jquery-3.7.1.min.js
taguette/static/js/jquery-3.7.1.min.js.map
taguette/static/js/taguette.js
taguette/static/missing.png
taguette/static/robots.txt
taguette/static/webfonts/BadScript-OFL.txt
taguette-1.5.2.dist-info/METADATA
taguette-1.5.2.dist-info/WHEEL
taguette-1.5.2.dist-info/entry_points.txt
taguette-1.5.2.dist-info/licenses/LICENSE.txt
taguette-1.5.2.dist-info/RECORD
