Metadata-Version: 2.4
Name: taguette
Version: 1.5.2
Summary: Free and open source qualitative research tool
License: BSD-3-Clause
License-File: LICENSE.txt
Keywords: qualitative,document,text,tagging,tags,highlights,notes
Author: Remi Rampin
Author-email: remi@rampin.org
Requires-Python: >=3.7,<4
Classifier: Development Status :: 5 - Production/Stable
Classifier: Environment :: Web Environment
Classifier: Intended Audience :: End Users/Desktop
Classifier: Intended Audience :: Science/Research
Classifier: License :: OSI Approved :: BSD License
Classifier: Operating System :: OS Independent
Classifier: Programming Language :: JavaScript
Classifier: Programming Language :: Python :: 3
Classifier: Programming Language :: Python :: 3.7
Classifier: Programming Language :: Python :: 3.8
Classifier: Programming Language :: Python :: 3.9
Classifier: Programming Language :: Python :: 3.10
Classifier: Programming Language :: Python :: 3.11
Classifier: Programming Language :: Python :: 3.12
Classifier: Programming Language :: Python :: 3.13
Classifier: Programming Language :: Python :: 3.14
Classifier: Programming Language :: Python :: 3 :: Only
Classifier: Topic :: Scientific/Engineering :: Information Analysis
Classifier: Topic :: Scientific/Engineering :: Visualization
Classifier: Topic :: Text Processing
Provides-Extra: mysql
Provides-Extra: otel
Provides-Extra: postgres
Requires-Dist: SQLAlchemy (>=1.4,<1.5)
Requires-Dist: XlsxWriter (>=1.4,<4)
Requires-Dist: alembic (>=1.6,<1.9)
Requires-Dist: beautifulsoup4
Requires-Dist: bleach (>=3,<6)
Requires-Dist: chardet (>=4,<6)
Requires-Dist: cryptography ; extra == "mysql"
Requires-Dist: html5lib (>=1,<2)
Requires-Dist: importlib-resources
Requires-Dist: jinja2 (>=3.1,<3.2)
Requires-Dist: opentelemetry-api (>=1.5,<1.11)
Requires-Dist: opentelemetry-distro ; extra == "otel"
Requires-Dist: opentelemetry-instrumentation-sqlalchemy (>=0.24b0,<0.26) ; extra == "otel"
Requires-Dist: opentelemetry-instrumentation-tornado (>=0.24b0,<0.26) ; extra == "otel"
Requires-Dist: prometheus-async
Requires-Dist: prometheus-client
Requires-Dist: psycopg2 (>=2.8,<3) ; extra == "postgres"
Requires-Dist: pymysql (>=1.0,<2) ; extra == "mysql"
Requires-Dist: redis (>=3,<5)
Requires-Dist: sentry-sdk
Requires-Dist: subtitle-parser (>=1,<3)
Requires-Dist: tornado (>=6.1)
Project-URL: Bug Tracker, https://gitlab.com/remram44/taguette/-/issues
Project-URL: Chat, https://app.element.io/#/room/#taguette:matrix.org
Project-URL: Documentation, https://www.taguette.org/getting-started.html
Project-URL: Homepage, https://www.taguette.org/
Project-URL: Open Collective, https://opencollective.com/taguette
Project-URL: Repository, https://gitlab.com/remram44/taguette
Project-URL: User Mailing List, https://groups.io/g/taguette
